LICENSE
MANIFEST.in
pytest.ini
requires.txt
setup.py
tox.ini
flask_restaction/__init__.py
flask_restaction/api.py
flask_restaction/auth.py
flask_restaction/cli.py
flask_restaction/exporters.py
flask_restaction/res.py
flask_restaction.egg-info/PKG-INFO
flask_restaction.egg-info/SOURCES.txt
flask_restaction.egg-info/dependency_links.txt
flask_restaction.egg-info/entry_points.txt
flask_restaction.egg-info/not-zip-safe
flask_restaction.egg-info/requires.txt
flask_restaction.egg-info/top_level.txt
flask_restaction/docs/docs.html
flask_restaction/docs/dist/docs.css
flask_restaction/docs/dist/docs.js
flask_restaction/docs/dist/docs.min.css
flask_restaction/docs/dist/docs.min.js
flask_restaction/docs/dist/highlight.min.js
flask_restaction/docs/dist/iconfont.eot
flask_restaction/docs/dist/iconfont.ttf
flask_restaction/docs/dist/marked.min.js
flask_restaction/docs/dist/pace.min.js
flask_restaction/docs/dist/vue.min.js
flask_restaction/resjs/dist/index.js
flask_restaction/resjs/dist/res.node.js
flask_restaction/resjs/dist/res.rn.js
flask_restaction/resjs/dist/res.web.js
flask_restaction/resjs/dist/res.web.min.js